{"markers":[ { 
"latitude":18.13705, "longitude":-94.434458, "title":"Auto Servicio Zaragoza E.S. 3995", "content":"Zaragoza Esq. Aquiles Serdan S/N Col. Centro, Coatzacoalcos, Ver.<br /> Premium - Magna" },
 { "latitude":18.138928, "longitude":-94.434339, "title":"Auto Servicio Abasolo E.S. 0410", "content":"Juarez Esq. Abasolo S/N Col. Centro, Coatzacoalcos, Ver.<br /> Premium - Magna" },
 { "latitude":18.114886, "longitude":-94.446911, "title":"Auto Servicio Terranova E.S. 2952", "content":"Juarez Esq. Abasolo S/N Col. Centro, Coatzacoalcos, Ver.<br /> Premium - Magna" },
 { "latitude":18.128592, "longitude":-94.438739, "title":"Auto Servicio Desnivel E.S. 2755", "content":"Carr. Coatzacoalcos-Minatitlan Km. 3.5 Col. Primero de Mayo, Coatzacoalcos, Ver." } ,
 { "latitude":17.990938, "longitude":-92.931783, "title":"Auto Servicio Grijalva E.S. 1067", "content":"Ave. Paseo Tabasco 906 Col. Jesus Garcia, Villahermosa Tab.<br /> Premium - Magna" },
  { "latitude":17.989583, "longitude":-92.949564, "title":"Auto Servicio Faja de Oro E.S. 1064", "content":"Ave. Rodolfo Ruiz Cortines 1418 Col. Atasta, Villahermosa Tab.<br /> Premium - Magna - Diesel" } ]}